lesson_package/__init__.py
lesson_package/main.py
python_lesson_15-0.0.1.dist-info/METADATA
python_lesson_15-0.0.1.dist-info/WHEEL
python_lesson_15-0.0.1.dist-info/license
python_lesson_15-0.0.1.dist-info/top_level.txt
python_lesson_15-0.0.1.dist-info/RECORD
