Metadata-Version: 2.1
Name: python-lesson-15
Version: 0.0.1
Summary: Package for test
Home-page: UNKNOWN
Author: Daniil Kimstach
Author-email: daniilkimstachp@gmail.com
License: UNKNOWN
Platform: UNKNOWN
Classifier: Programming Language :: Python :: 3.8
Classifier: License :: OSI Approved :: MIT License
Classifier: Operating System :: OS Independent
Requires-Python: >=3.6
